{"TX":"partial_research_complete","VA":"partial_research_complete","GA":"lead_scan_complete","AZ":"lead_scan_complete","OH":"lead_scan_complete","TN":"lead_scan_complete","IA":"lead_scan_complete","OR":"lead_scan_complete","WA":"lead_scan_complete","NC":"lead_scan_complete","NV":"lead_scan_complete","UT":"lead_scan_complete","IL":"lead_scan_complete","IN":"lead_scan_complete","PA":"lead_scan_complete","NY":"lead_scan_complete","AL":"lead_scan_complete","LA":"lead_scan_complete","MS":"lead_scan_complete"}
